vscode_pytest_update_snapshot/__init__.py
vscode_pytest_update_snapshot/__main__.py
vscode_pytest_update_snapshot-0.2.0.dist-info/licenses/LICENSE
vscode_pytest_update_snapshot-0.2.0.dist-info/METADATA
vscode_pytest_update_snapshot-0.2.0.dist-info/WHEEL
vscode_pytest_update_snapshot-0.2.0.dist-info/entry_points.txt
vscode_pytest_update_snapshot-0.2.0.dist-info/top_level.txt
vscode_pytest_update_snapshot-0.2.0.dist-info/RECORD
