Metadata-Version: 2.4
Name: vscode-pytest-update-snapshot
Version: 0.2.0
Summary: Run pytest on the test at cursor and update inline snapshots.
Author-email: David Walker <dbwalker0min@gmail.com>
License: MIT
Requires-Python: >=3.12
License-File: LICENSE
Requires-Dist: typer>=0.19.2
Dynamic: license-file
